fast_router/__init__.py
fast_router/analyzer.py
fast_router/fast_router.py
fast_router-0.3.0.dist-info/licenses/LICENSE
fast_router-0.3.0.dist-info/METADATA
fast_router-0.3.0.dist-info/WHEEL
fast_router-0.3.0.dist-info/top_level.txt
fast_router-0.3.0.dist-info/RECORD
