Metadata-Version: 2.4
Name: fast-router
Version: 0.3.0
Summary: A simple and intuitive file-based router for FastAPI applications.
Author-email: Lftobs <noreply@github.com>
License-Expression: MIT
Project-URL: Homepage, https://lftobs.github.io/FastRouter/
Project-URL: Repository, https://github.com/Lftobs/FastRouter
Project-URL: Issues, https://github.com/Lftobs/FastRouter/issues
Project-URL: Documentation, https://lftobs.github.io/FastRouter/
Classifier: Development Status :: 4 - Beta
Classifier: Intended Audience :: Developers
Classifier: Operating System :: OS Independent
Classifier: Programming Language :: Python :: 3
Classifier: Programming Language :: Python :: 3.11
Classifier: Programming Language :: Python :: 3.12
Classifier: Programming Language :: Python :: 3.13
Classifier: Programming Language :: Python :: 3 :: Only
Classifier: Framework :: FastAPI
Classifier: Topic :: Internet :: WWW/HTTP :: HTTP Servers
Classifier: Topic :: Software Development :: Libraries :: Python Modules
Classifier: Topic :: Software Development :: Libraries :: Application Frameworks
Classifier: Typing :: Typed
Requires-Python: >=3.13
License-File: LICENSE
Requires-Dist: fastapi>=0.116.1
Requires-Dist: tree-sitter>=0.25.2
Requires-Dist: tree-sitter-python>=0.25.0
Requires-Dist: uvicorn>=0.35.0
Dynamic: license-file
